accepts/__init__.py
afk_tracker/__init__.py
afk_tracker/apps.py
afk_tracker/classes.py
afk_tracker/models.py
afk_tracker/setup.py
afk_tracker/migrations/0001_initial.py
afk_tracker/migrations/__init__.py
applescript/__init__.py
applescript/tell.py
stdin/__init__.py
applescript-2019.3.22.dist-info/METADATA
applescript-2019.3.22.dist-info/WHEEL
applescript-2019.3.22.dist-info/top_level.txt
applescript-2019.3.22.dist-info/RECORD
