Metadata-Version: 2.1
Name: applescript
Version: 2019.3.22
Summary: run applescript
Home-page: https://github.com/looking-for-a-job/applescript.py
License: UNKNOWN
Keywords: applescript
Platform: UNKNOWN
Classifier: License :: Public Domain
Classifier: Operating System :: MacOS
Classifier: Programming Language :: Python
Classifier: Programming Language :: Python :: 2
Classifier: Programming Language :: Python :: 2.7
Classifier: Programming Language :: Python :: 3
Classifier: Programming Language :: Python :: 3.4
Classifier: Programming Language :: Python :: 3.5
Classifier: Programming Language :: Python :: 3.6
Classifier: Programming Language :: Python :: 3.7
Classifier: Topic :: Software Development
Requires-Dist: only
Requires-Dist: public
Requires-Dist: runcmd
Requires-Dist: setuptools
Requires-Dist: temp
